Metadata-Version: 2.1
Name: PyEclipse
Version: 0.1.1
Summary: Krótki opis twojego projektu
Home-page: https://github.com/twoj_github/nazwa_projektu
Author: SneakyFrameworkCreator
Author-email: twoj_email@example.com
Classifier: Programming Language :: Python :: 3
Classifier: License :: OSI Approved :: MIT License
Classifier: Operating System :: OS Independent
Requires-Python: >=3.12
